nc_helpers/authentik.py
nc_helpers/dict_access.py
nc_helpers/helper_functions.py
nc_helpers/librenms.py
nc_helpers/logger.py
nc_helpers/netbox.py
nc_helpers/port_profiles.py
nc_helpers/prisma.py
nc_helpers/diffsync_definition/adapters.py
nc_helpers/diffsync_definition/devicetype_mapping.yaml
nc_helpers/diffsync_definition/exceptions.py
nc_helpers/diffsync_definition/models.py
nc_helpers-1.2.dist-info/licenses/LICENCE
nc_helpers-1.2.dist-info/METADATA
nc_helpers-1.2.dist-info/WHEEL
nc_helpers-1.2.dist-info/top_level.txt
nc_helpers-1.2.dist-info/RECORD
