Metadata-Version: 2.4
Name: nc-helpers
Version: 1.2
Summary: helper function for ncubed software
Author-email: Jasper Schoenmaker <jasper.schoenmaker@ncubed.nl>
License: GPL-3.0 license
Keywords: ncubed,helpers,mis,nc_accelerator
Classifier: Programming Language :: Python :: 3
Requires-Python: >=3.10
License-File: LICENCE
Requires-Dist: diffsync>=2.0.0
Requires-Dist: requests>=2.32.3
Requires-Dist: python-dotenv>=1.0.1
Requires-Dist: pyyaml>=6.0.3
Requires-Dist: python-slugify
Requires-Dist: twine>=6.2.0
Dynamic: license-file
